{
  "new": [
    {
      "no": 1,
      "name": "윈터 페이버릿 하이볼",
      "price": "6,500원",
      "info": "[Only ICED] 프레시한 레몬과 스모키한 위스키 향이 조화로운 무알콜 하이볼 에이드 음료",
      "image": ""
    },
    {
      "no": 2,
      "name": "윈터 페이버릿 뱅쇼",
      "price": "6,300원",
      "info": "깊은 레드 와인의 맛과 달콤한 과일, 은은한 시나몬 향이 조화롭게 어우러진 무알콜 뱅쇼 음료",
      "image": ""
    },
    {
      "no": 3,
      "name": "자스민 시트러스 티",
      "price": "6,300원",
      "info": "은은한 자스민향이 더해진 우롱티에 유자와 레몬을 더해 달콤하게 즐길 수 있는 티 음료",
      "image": ""
    },
    {
      "no": 4,
      "name": "카페 에그노그",
      "price": "6,300원",
      "info": "진한 롱블랙에 달콤한 에그노그 크림을 더해 투썸 스타일로 재해석한 크리스마스 전통 커피",
      "image": ""
    },
    {
      "no": 5,
      "name": "스초생 프라페",
      "price": "6,100원",
      "info": "달콤한 스트로베리와 진한 초콜릿의 조화 속, 톡톡 씹히는 크런치를 함께 즐길 수 있는 프라페/어린이, 임산부, 카페인 민감자는 고카페인 함유 음료 섭취에 주의해 주시기 바랍니다.",
      "image": ""
    }
  ],
  "coffee": [
    {
      "no": 1,
      "name": "카페 에그노그",
      "price": "6,300원",
      "info": "진한 롱블랙에 달콤한 에그노그 크림을 더해 투썸 스타일로 재해석한 크리스마스 전통 커피",
      "image": ""
    },
    {
      "no": 2,
      "name": "올타임콜드브루",
      "price": "6,000원",
      "info": "[Only ICED] 콜드브루에 우유,연유,생크림을 넣어 달콤하게 카페인을 충전할 수 있는 콜드브루 라떼",
      "image": ""
    },
    {
      "no": 3,
      "name": "아인슈페너2023",
      "price": "6,100원",
      "info": "부드러운 라떼에 더욱 부드러운 크림을 듬뿍 얹은 라떼타입 아인슈페너",
      "image": ""
    },
    {
      "no": 4,
      "name": "(1호점)신촌커피",
      "price": "6,100원",
      "info": "투썸의 1호점 신촌에서 시작된 달콤한 첫 맛의 기억, 바닐라빈의 고급스러움을 더해 '(1호점)신촌 커피'",
      "image": ""
    },
    {
      "no": 5,
      "name": "아메리카노",
      "price": "4,500원",
      "info": "진하게 로스팅한 커피 원두에서 에스프레소를 추출하여 투썸 고유의 원두 풍미를 느낄 수 있는 에스프레소 음료/어린이, 임산부, 카페인 민감자는 고카페인 함유 음료 섭취에 주의해 주시기 바랍니다.",
      "image": ""
    },
    {
      "no": 6,
      "name": "카페라떼",
      "price": "5,000원",
      "info": "풍부하고 진한 농도의 에스프레소와 스팀밀크 위에 부드러운 우유 거품을 살짝 올려준 에스프레소 음료/어린이, 임산부, 카페인 민감자는 고카페인 함유 음료 섭취에 주의해 주시기 바랍니다.",
      "image": ""
    },
    {
      "no": 7,
      "name": "바닐라라떼",
      "price": "5,500원",
      "info": "달콤한 바닐라 향과 풍부한 에스프레소가 조화를 이룬 부드러운 라떼/어린이, 임산부, 카페인 민감자는 고카페인 함유 음료 섭취에 주의해 주시기 바랍니다.",
      "image": ""
    },
    {
      "no": 8,
      "name": "카페모카",
      "price": "5,500원",
      "info": "진한 초콜릿 모카시럽과 풍부하고 진한 농도의 에스프레소를 스팀밀크와 혼합한 달콤한 에스프레소 음료/어린이, 임산부, 카페인 민감자는 고카페인 함유 음료 섭취에 주의해 주시기 바랍니다.",
      "image": ""
    },
    {
      "no": 9,
      "name": "카라멜마끼야또",
      "price": "6,300원",
      "info": "바닐라 향을 넣은 스팀밀크 위에 에스프레소 샷을 넣고 카라멜 소스를 뿌린 달콤한 에스프레소 음료/어린이, 임산부, 카페인 민감자는 고카페인 함유 음료 섭취에 주의해 주시기 바랍니다.",
      "image": ""
    },
    {
      "no": 10,
      "name": "스페니쉬연유라떼",
      "price": "5,800원",
      "info": "평화로운 유럽초원의 감성을 담은 부드럽고 달콤한 라떼/어린이, 임산부, 카페인 민감자는 고카페인 함유 음료 섭취에 주의해 주시기 바랍니다.",
      "image": ""
    },
    {
      "no": 11,
      "name": "달고나라떼",
      "price": "6,000원",
      "info": "로스팅 슈가 향의 에스프레소 크림과 추억의 달고나가 어우러진 카페 라떼/어린이, 임산부, 카페인 민감자는 고카페인 함유 음료 섭취에 주의해 주시기 바랍니다.",
      "image": ""
    },
    {
      "no": 12,
      "name": "콜드브루",
      "price": "4,900원",
      "info": "[Only ICED]커피 본연의 깊은 풍미와 단맛이 느껴지는 부드럽고 깔끔한 콜드브루 커피/어린이, 임산부, 카페인 민감자는 고카페인 함유 음료 섭취에 주의해 주시기 바랍니다.",
      "image": ""
    },
    {
      "no": 13,
      "name": "콜드브루라떼",
      "price": "5,400원",
      "info": "[Only ICED]콜드브루와 우유가 어우러져 더욱 부드럽게 즐길 수 있는 콜드브루 라떼/어린이, 임산부, 카페인 민감자는 고카페인 함유 음료 섭취에 주의해 주시기 바랍니다.",
      "image": ""
    },
    {
      "no": 14,
      "name": "디카페인데이&나잇",
      "price": "6,000원",
      "info": "아침부터 저녁까지 부담 없이, SWP 디카페인 커피에 페퍼민트티를 더한 '디카페인 데이&나잇'",
      "image": ""
    },
    {
      "no": 15,
      "name": "디카페인오프화이트라떼",
      "price": "5,600원",
      "info": "디카페인 에스프레소에 고소한 귀리우유와 생크림을 더한 부드러운 카페라떼",
      "image": ""
    }
  ],
  "drink": [
    {
      "no": 1,
      "name": "스초생 프라페",
      "price": "6,100원",
      "info": "달콤한 스트로베리와 진한 초콜릿의 조화 속, 톡톡 씹히는 크런치를 함께 즐길 수 있는 프라페/어린이, 임산부, 카페인 민감자는 고카페인 함유 음료 섭취에 주의해 주시기 바랍니다.",
      "image": ""
    },
    {
      "no": 2,
      "name": "윈터 페이버릿 뱅쇼",
      "price": "6,300원",
      "info": "깊은 레드 와인의 맛과 달콤한 과일, 은은한 시나몬 향이 조화롭게 어우러진 무알콜 뱅쇼 음료",
      "image": ""
    },
    {
      "no": 3,
      "name": "윈터 페이버릿 하이볼",
      "price": "6,500원",
      "info": "[Only ICED] 프레시한 레몬과 스모키한 위스키 향이 조화로운 무알콜 하이볼 에이드 음료",
      "image": ""
    },
    {
      "no": 4,
      "name": "레몬바질스파클링",
      "price": "6,500원",
      "info": "상큼한 레몬과 향기로운 바질에 알룰로스를 더해 저당으로 즐기는 스파클링 음료",
      "image": ""
    },
    {
      "no": 5,
      "name": "청귤스파클링",
      "price": "6,300원",
      "info": "싱그러운 청귤에 알룰로스를 더해 저당으로 즐기는 스파클링 음료",
      "image": ""
    },
    {
      "no": 6,
      "name": "애플망고주스",
      "price": "6,300원",
      "info": "달콤한 애플 망고를 듬뿍 담아 산뜻하게 즐기는 애플 망고 주스",
      "image": ""
    },
    {
      "no": 7,
      "name": "20곡오틀리라떼",
      "price": "6,100원",
      "info": "20가지 곡물의 고소함을 오틀리 오트 음료와 함께 한 잔으로 즐길 수 있는 영양 충족 곡물 라떼",
      "image": ""
    },
    {
      "no": 8,
      "name": "오틀리모카프라페",
      "price": "6,500원",
      "info": "[Only ICED] 달콤한 초코, 에스프레소, 오트 우유를 바삭한 곡물 토핑과 시원하게 즐기는 프라페",
      "image": ""
    },
    {
      "no": 9,
      "name": "민트초코프라페",
      "price": "5,800원",
      "info": "상쾌한 민트향과 진한 초콜릿을 한번에 즐길 수 있는 달콤한 프라페",
      "image": ""
    },
    {
      "no": 10,
      "name": "복숭아에이드",
      "price": "6,000원",
      "info": "천도 복숭아를 듬뿍 넣어 아삭한 식감이 그대로 느껴지는 달콤하고 청량한 과일 에이드",
      "image": ""
    },
    {
      "no": 11,
      "name": "샤인머스캣청포도에이드",
      "price": "6,300원",
      "info": "달콤함이 가득한 샤인머스캣과 청포도, 탄산수가 만나 상큼하고 청량한 과일 에이드",
      "image": ""
    },
    {
      "no": 12,
      "name": "아이스버블그린티라떼",
      "price": "5,900원",
      "info": "깔끔한 녹차향과 부드러운 우유가 입안 가득 조화를 이룬 티 라떼에 쫀득한 타피오카를 넣어 씹는 재미를 더한 음료/어린이, 임산부, 카페인 민감자는 고카페인 함유 음료 섭취에 주의해 주시기 바랍니다.",
      "image": ""
    },
    {
      "no": 13,
      "name": "스트로베리피치프라페",
      "price": "6,100원",
      "info": "딸기와 복숭아의 상큼함이 조화롭게 어우러진 스무디 타입의 스트로베리피치프라페",
      "image": ""
    },
    {
      "no": 14,
      "name": "요거트프라페",
      "price": "5,800원",
      "info": "요거 파우더와 우유가 조화된 깔끔하고 상큼한 맛의 요거트 아이스 블렌디드",
      "image": ""
    },
    {
      "no": 15,
      "name": "망고프라페",
      "price": "6,000원",
      "info": "열대 망고의 시원한 맛을 느낄 수 있는 망고프라페",
      "image": ""
    },
    {
      "no": 16,
      "name": "바닐라밀크쉐이크",
      "price": "5,600원",
      "info": "바닐라 아이스크림과 우유를 블렌딩한 부드럽고 달콤한 바닐라쉐이크",
      "image": ""
    },
    {
      "no": 17,
      "name": "초코밀크쉐이크",
      "price": "5,600원",
      "info": "바닐라 아이스크림과 발로나 초콜릿의 진한 풍미를 즐길 수 있는 쉐이크/어린이, 임산부, 카페인 민감자는 고카페인 함유 음료 섭취에 주의해 주시기 바랍니다.",
      "image": ""
    },
    {
      "no": 18,
      "name": "로얄밀크티쉐이크",
      "price": "6,500원",
      "info": "은은한 얼그레이 향이 감도는 블랙티와 진한 소프트 아이스크림이 어우러진 투썸 아이스크림 디저트 음료/어린이, 임산부, 카페인 민감자는 고카페인 함유 음료 섭취에 주의해 주시기 바랍니다.",
      "image": ""
    },
    {
      "no": 19,
      "name": "자몽에이드",
      "price": "5,800원",
      "info": "자몽의 상큼함과 청량감이 입안 가득 느껴지는 자몽에이드",
      "image": ""
    },
    {
      "no": 20,
      "name": "오렌지에이드",
      "price": "5,800원",
      "info": "오렌지를 그대로 갈아 넣은 상큼한 오렌지 에이드",
      "image": ""
    },
    {
      "no": 21,
      "name": "오렌지자몽주스",
      "price": "6,300원",
      "info": "통 오렌지와 자몽을 블렌딩한 상큼함이 입안 가득 느껴지는 주스",
      "image": ""
    },
    {
      "no": 22,
      "name": "키위바나나주스",
      "price": "5,800원",
      "info": "그린키위와 바나나가 블렌딩 된 주스",
      "image": ""
    },
    {
      "no": 23,
      "name": "블루베리요거트드링크",
      "price": "5,300원",
      "info": "깊고 진한 블루베리 풍미와 요거트의 조화를 느낄 수 있는 음료",
      "image": ""
    },
    {
      "no": 24,
      "name": "플레인요거트드링크",
      "price": "4,800원",
      "info": "요거트의 깊은 풍미를 즐길 수 있는 음료",
      "image": ""
    },
    {
      "no": 25,
      "name": "아이스버블밀크티",
      "price": "6,000원",
      "info": "향긋한 홍차와 부드러운 우유가 입안 가득 조화를 이룬 티 라떼에 쫀득한 타피오카를 넣어 씹는 재미를 더한 음료/어린이, 임산부, 카페인 민감자는 고카페인 함유 음료 섭취에 주의해 주시기 바랍니다.",
      "image": ""
    }
  ],
  "tee": [
    {
      "no": 1,
      "name": "자스민 시트러스 티",
      "price": "6,300원",
      "info": "은은한 자스민향이 더해진 우롱티에 유자와 레몬을 더해 달콤하게 즐길 수 있는 티 음료",
      "image": ""
    },
    {
      "no": 2,
      "name": "싱가포르 블랙퍼스트",
      "price": "5,100원",
      "info": "홍차와 바닐라가 조화로우면서도 스파이시한 여운이 부드럽게 남는 스트레이트 티",
      "image": ""
    },
    {
      "no": 3,
      "name": "엘더플라워 블랙티",
      "price": "6,500원",
      "info": "향긋한 엘더플러워, 상큼한 유자와 레몬이 싱가포르 브렉퍼스트와 어우러진 가을 시즌 블렌딩 티",
      "image": ""
    },
    {
      "no": 4,
      "name": "임페리얼우롱",
      "price": "5,100원",
      "info": "밸런스와 풍미가 좋은 반 발효 우롱 스트레이트 티",
      "image": ""
    },
    {
      "no": 5,
      "name": "우롱크림티",
      "price": "6,500원",
      "info": "[Only ICED] 반 발효된 우롱티와 부드러운 크림이 어우러져 깔끔하면서도 풍부한 맛을 느낄 수 있는 크림 밀크 티",
      "image": ""
    },
    {
      "no": 6,
      "name": "피치블랙티",
      "price": "6,000원",
      "info": "달콤한 복숭아에 향기로운 우롱 블랙티를 조화롭게 즐길 수 있는 베리에이션 티",
      "image": ""
    },
    {
      "no": 7,
      "name": "잉글리쉬브렉피스트",
      "price": "5,100원",
      "info": "전통적인 영국의 아침에 어울리도록 블랜딩 된 차, 맛이 진하고 바디감이 강한 것이 특징/어린이, 임산부, 카페인 민감자는 고카페인 함유 음료 섭취에 주의해 주시기 바랍니다.",
      "image": ""
    },
    {
      "no": 8,
      "name": "제주유기농녹차",
      "price": "4,800원",
      "info": "청정 제주산 유기농 녹차 100%, 이른 봄에 채엽한 어린잎 첫물차로 만들어 떫은 맛이 적고 깊고 풍부한 감칠맛의 고급 녹차",
      "image": ""
    },
    {
      "no": 9,
      "name": "초콜릿라떼",
      "price": "5,200원",
      "info": "초콜릿의 풍부한 맛과 초코칩이 조화로운 달콤한 초콜릿 음료/어린이, 임산부, 카페인 민감자는 고카페인 함유 음료 섭취에 주의해 주시기 바랍니다.",
      "image": ""
    },
    {
      "no": 10,
      "name": "그린티라떼",
      "price": "5,200원",
      "info": "그린티 파우더를 고운 거품으로 녹여준 뒤 스팀우유를 붓고 우유거품으로 마무리한 부드러운 티라떼/어린이, 임산부, 카페인 민감자는 고카페인 함유 음료 섭취에 주의해 주시기 바랍니다.",
      "image": ""
    },
    {
      "no": 11,
      "name": "로얄밀크티",
      "price": "5,500원",
      "info": "향긋한 홍차향이 부드러운 우유와 어우러진 정통 밀크티/어린이, 임산부, 카페인 민감자는 고카페인 함유 음료 섭취에 주의해 주시기 바랍니다.",
      "image": ""
    },
    {
      "no": 12,
      "name": "허니레몬티",
      "price": "6,100원",
      "info": "진한 TWG 프렌치 얼그레이 베이스에 달콤한 꿀과 상큼한 레몬이 더해진 티",
      "image": ""
    },
    {
      "no": 13,
      "name": "카모마일",
      "price": "6,300원",
      "info": "카페인이 없어 누구나 편안하게 즐길 수 있는 허브티로, 풍부한 벌꿀향과 황금빛이 특징인 TWG TEA",
      "image": ""
    },
    {
      "no": 14,
      "name": "크림카라멜",
      "price": "5,100원",
      "info": "남아프리카 공화국의 루이보스 차에 달콤한 카라멜을 블렌딩하여 매력적이고 섬세함을 지닌 TWG TEA",
      "image": ""
    },
    {
      "no": 15,
      "name": "프렌치얼그레이",
      "price": "5,100원",
      "info": "TWG TEA의 대표적인 얼그레이 계열의 홍차. 클래식하면서 우아한 시트러스 과일향과 수레국화의 향긋한 향이 특징인 TEA/어린이, 임산부, 카페인 민감자는 고카페인 함유 음료 섭취에 주의해 주시기 바랍니다.",
      "image": ""
    },
    {
      "no": 16,
      "name": "그나와민트티",
      "price": "5,100원",
      "info": "홍차, 녹차, 민트가 블렌딩 된 청량한 타입의 TWG TEA/어린이, 임산부, 카페인 민감자는 고카페인 함유 음료 섭취에 주의해 주시기 바랍니다.",
      "image": ""
    },
    {
      "no": 17,
      "name": "애플민트티",
      "price": "6,100원",
      "info": "TWG 그나와 민트티와 애플이 어우러진 베리에이션 티",
      "image": ""
    },
    {
      "no": 18,
      "name": "유자레몬티",
      "price": "5,500원",
      "info": "달콤 쌉싸름한 유자청과 레몬즙이 어우러진 상큼한 시트러스 티",
      "image": ""
    },
    {
      "no": 19,
      "name": "오렌지자몽티",
      "price": "5,500원",
      "info": "블러드 오렌지와 자몽을 그대로 착즙하여 따뜻하게 즐길 수 있는 과일 티",
      "image": ""
    },
    {
      "no": 20,
      "name": "쑥라떼",
      "price": "5,500원",
      "info": "향긋한 쑥의 풍미와 부드러운 우유가 조화롭게 어우러지는 쑥 라떼",
      "image": ""
    },
    {
      "no": 21,
      "name": "고구마라떼",
      "price": "5,500원",
      "info": "고구마를 통째로 갈아넣어 원물감이 살아있는 리얼 라떼",
      "image": ""
    }
  ],
  "wholecake": [
    {
      "no": 1,
      "name": "화이트 쇼콜라 무스",
      "price": "43,000원",
      "info": "바닐라 크림과 딸기 라임 꿀리를 넣은 베리무스로 상큼함을 더하고 발로나 초코볼을 넣어 재미있는 식감을 살린 시즌 대표 케이크",
      "image": ""
    },
    {
      "no": 2,
      "name": "홀리데이 위시 캔들",
      "price": "37,000원",
      "info": "프랄린이 들어가 고소한 견과류 맛의 부드러운 시트에 가나슈 몽떼, 솔티카라멜, 피칸을 샌드하여 맛과 재미난 식감을 더한 캔들 모양의 케이크",
      "image": ""
    },
    {
      "no": 3,
      "name": "민트볼 가토 쇼콜라",
      "price": "37,000원",
      "info": "촉촉하고 묵직한 초코시트, 쫀득한 초코 가나슈, 카라멜 크림으로 맛을내고, 반을 갈랐을 때 숨어있는 초코 구슬이 나와 재미를 더한 홀케이크",
      "image": ""
    },
    {
      "no": 4,
      "name": "화이트 포레스트 트리",
      "price": "39,000원",
      "info": "입체로 만든 화이트 초콜릿 트리와 코코넛 파우더를 사용해 눈 덮인 하얀 숲을 연상시키며 진한 다크 초콜릿무스와 체리쥬레, 화이트 초콜릿 무스가 조화롭게 어우러지는 무스 케이크",
      "image": ""
    },
    {
      "no": 5,
      "name": "TWG 1837 블랙티 무스",
      "price": "37,000원",
      "info": "TWG 1837 블랙티를 진하게 우려낸 밀크티 초콜릿 무스와 향기롭고 촉촉한 피치&라즈베리 콤포트가 밸런스를 이루는 TWG 시그니처 틴케이스를 형상화한 무스 케이크",
      "image": ""
    },
    {
      "no": 6,
      "name": "샤인머스캣 마스카포네 생크림",
      "price": "37,000원",
      "info": "상큼한 샤인머스캣이 한가득 올라간 마스카포네 생크림 케이크",
      "image": ""
    },
    {
      "no": 7,
      "name": "파티팩샤인머스캣우유생크림",
      "price": "40,200원",
      "info": "누구나 호불호 없이 즐길 수 있는 대중적인 고단백 저지방 우유를 활용한 우유 베이스에 샤인머스캣을 가득 올린 가볍고 산뜻한 Summer Dessert",
      "image": ""
    },
    {
      "no": 8,
      "name": "파티팩딸기우유생크림",
      "price": "40,200원",
      "info": "누구나 호불호 없이 즐길 수 있는 대중적인 고단백 저지방 우유를 활용한 우유 베이스에 딸기 가득 올린 가볍고 산뜻한 Dessert",
      "image": ""
    },
    {
      "no": 9,
      "name": "옥수수바스크치즈케이크",
      "price": "38,000원",
      "info": "옥수수의 풍미를 담은 묵직한 바스크 치즈 케이크에 고소한 옥수수 크림을 가득 올린 홈메이드 스타일의 치즈 케이크",
      "image": ""
    },
    {
      "no": 10,
      "name": "샤인머스캣우유생크림",
      "price": "37,000원",
      "info": "순백의 시트 사이사이 순우유, 딸기우유 무스와 생크림으로 가득 채운 케이크 위에 샤인머스캣을 한가득 올린 케이크",
      "image": ""
    },
    {
      "no": 11,
      "name": "베리우유생크림",
      "price": "37,000원",
      "info": "순백의 시트 사이사이 순우유, 딸기우유 무스와 생크림으로 가득 채운 케이크 위에 믹스드베리를 한가득 올린 케이크",
      "image": ""
    },
    {
      "no": 12,
      "name": "초콜릿링딩동",
      "price": "36,000원",
      "info": "미국식 홈메이드 레시피 DING DONG Cake를 재해석 진한 초콜릿 시트와 부드러운 생크림을 레이어하고 초콜릿 가나슈로 도톰하게 코팅하여 깊고 풍부한 맛을 구현한 초코릿 러버들을 위한 케이크",
      "image": ""
    },
    {
      "no": 13,
      "name": "베리초콜릿링딩동",
      "price": "36,000원",
      "info": "미국식 홈메이드 레시피 DING DONG Cake를 재해석 진한 초콜릿 시트와 부드러운 생크림을 레이어하고 초콜릿 가나슈로 도톰하게 코팅하여 깊고 풍부한 맛을 구현한 초코릿 러버들을 위한 케이크",
      "image": ""
    },
    {
      "no": 14,
      "name": "더블랙그뤼에르치즈",
      "price": "37,000원",
      "info": "겉은 블랙 초코 크런치로 커버하고, 안은 화이트 그뤼에르 치즈 무스와 시트를 레이어하여 진하고 부드럽게 즐기는 무스케이크",
      "image": ""
    },
    {
      "no": 15,
      "name": "빅토리아다쿠아즈초콜릿생크림(익스트베리)",
      "price": "38,000원",
      "info": "가나슈 생크림과 초코칩 헤이즐넛 페이틴이 어우러져 쫀득하고 바삭한 초콜릿 다쿠아즈 케이크에 상큼한 믹스드베리를 곁들여 먹는 생크림 케이크",
      "image": ""
    },
    {
      "no": 16,
      "name": "베리마스카포네생크림",
      "price": "37,000원",
      "info": "상큼한 믹스드베리가 가득 올라간 마스카포네 생크림 케이크 1호",
      "image": ""
    },
    {
      "no": 17,
      "name": "샤인머스캣초콜릿생크림",
      "price": "37,000원",
      "info": "한가득 올린 달콤상큼한 샤인머스캣, 크런치 초코볼이 초코 생크림 사이사이씹히는 투썸 베스트 생크림 케이크",
      "image": ""
    },
    {
      "no": 18,
      "name": "그릭요거트딸기생크림",
      "price": "34,000원",
      "info": "딸기, 블루베리와 상큼한 베리 쥬레가 샌드되어 베리와 요거 생크림의 맛을 조화롭게 느낄 수 있는 생크림 케이크",
      "image": ""
    },
    {
      "no": 19,
      "name": "파티팩바닐라슈크림",
      "price": "39,000원",
      "info": "달콤한 슈크림과 바닐라 무스, 폭신한 케이크 시트를 레이어하고 부드러운 생크림을 올려, 고소하고 바삭한 쿠키와 함께 즐기는 풍성한 구성의 떠먹는 케이크",
      "image": ""
    },
    {
      "no": 20,
      "name": "쿠키 앤 크림",
      "price": "35,000원",
      "info": "촉촉한 초코시트와 묵직한 블랙 초코시트 사이에 부드러운 크림치즈 크림과 블랙쿠키 크럼블이 듬뿍 믹스되어 부드럽게 즐길 수 있는 달콤한 쿠키앤크림 케이크",
      "image": ""
    },
    {
      "no": 21,
      "name": "고구마 밀크 생크림",
      "price": "35,000원",
      "info": "달콤하고 묵직한 고구마 무스 크림과 담백한 생크림의 조화로 남녀노소 누구나 밋있게 즐길 수 있는 고구마 생크림 케이크",
      "image": ""
    },
    {
      "no": 22,
      "name": "마이 투썸 하트",
      "price": "37,000원",
      "info": "투썸의 베스트 케이크를 모두 함께 맛볼 수 있는 다채로운 조합의 홀케이크",
      "image": ""
    },
    {
      "no": 23,
      "name": "파티팩티라미수",
      "price": "39,000원",
      "info": "마스카포네 치즈와 진한 에스프레소 시럽으로 샌드된 촉촉한 시트 위에 순도 높은 발로나 파우더를 올린 이탈리아 대표 무스 케이크 티라미수",
      "image": ""
    },
    {
      "no": 24,
      "name": "파티팩아이스박스",
      "price": "39,000원",
      "info": "블랙쿠키 층에 마스카포네 크림의 수분이 전이되어 촉촉하고 부드럽게 즐기는 아이스박스",
      "image": ""
    },
    {
      "no": 25,
      "name": "클래식가토쇼콜라",
      "price": "36,000원",
      "info": "부드러운 초코 시트에 벨기에산 다크&밀크 초콜릿 가나슈를 샌드하여 달콤하고 진하게 즐기는 초콜릿 케이크",
      "image": ""
    },
    {
      "no": 26,
      "name": "파티팩딸기레어치즈",
      "price": "39,000원",
      "info": "상큼한 딸기퓨레와 부드러운 크림치즈, 고소한 크럼블, 라즈베리가 함께 어울려 봄을 닮은 맛의 딸기레어치즈",
      "image": ""
    },
    {
      "no": 27,
      "name": "마스카포네티라미수",
      "price": "37,000원",
      "info": "마스카포네 치즈와 진한 에스프레소 시럽으로 샌드된 촉촉한 시트 위에 순도 높은 발로나 파우더를 올린 이탈리아 대표 무스 케이크",
      "image": ""
    },
    {
      "no": 28,
      "name": "레드벨벳",
      "price": "36,000원",
      "info": "붉은 컬러 시트에 고소한 버터 크림치즈를 풍부하게 올려 볼륨감이 돋보이는 투썸 대표 구움 케이크",
      "image": ""
    },
    {
      "no": 29,
      "name": "뉴욕치즈",
      "price": "37,000원",
      "info": "부드럽고 촉촉한 식감과 진한 치즈의 향이 물씬 나는 정통 뉴욕 스타일의 구움치즈 케이크",
      "image": ""
    },
    {
      "no": 30,
      "name": "퀸즈캐롯",
      "price": "36,000원",
      "info": "담백한 당근과 상큼한 오렌지 필로 식감을 살린 촉촉한 캐롯 시트와 묵직한 크림치즈를 풍성하게 레이어한 영국식 티 케이크",
      "image": ""
    },
    {
      "no": 31,
      "name": "베리생크림",
      "price": "34,000원",
      "info": "담백한 생크림과 부드러운 시트에 믹스드베리를 풍성하게 올린 생크림 케이크",
      "image": ""
    },
    {
      "no": 32,
      "name": "체리우유생크림",
      "price": "37,000원",
      "info": "순백의 시트 사이사이 순우유, 딸기우유 무스와 생크림으로 가득 채운 케이크 위에 제철 생딸기를 한가득 올린 스트로베리 시즌 대표 케이크",
      "image": ""
    }
  ],
  "pieceofcake": [
    {
      "no": 1,
      "name": "솔티드 카라멜 생크림",
      "price": "6,500원",
      "info": "프랄린이 들어가 고소한 견과류 맛의 부드러운 시트에 가나슈 몽떼, 솔티카라멜, 피칸을 샌드하여 맛과 재미난 식감을 더한 케이크",
      "image": ""
    },
    {
      "no": 2,
      "name": "카라멜 가토 쇼콜라",
      "price": "6,500원",
      "info": "촉촉하고 묵직한 초코시트, 쫀득한 초코 가나슈, 카라멜 크림으로 맛을내고, 반을 갈랐을 때 숨어있는 초코 구슬이 나와 재미를 더한 조각케이크",
      "image": ""
    },
    {
      "no": 3,
      "name": "TWG 1837 블랙티 무스",
      "price": "6,500원",
      "info": "TWG 1837 블랙티를 진하게 우려낸 밀크티 초콜릿 무스와 향기롭고 촉촉한 피치&라즈베리 콤포트가 밸런스를 이루는 무스 케이크",
      "image": ""
    },
    {
      "no": 4,
      "name": "다쿠아즈 초콜릿 생크림(딸기)",
      "price": "6,700원",
      "info": "가나슈 생크림과 초코칩 헤이즐넛 페이틴이 어우러져 쫀득하고 바삭한 초콜릿 다쿠아즈 케이크에 상큼한 딸기를 곁들여 먹는 케이크",
      "image": ""
    },
    {
      "no": 5,
      "name": "옥수수 바스크 치즈",
      "price": "6,700원",
      "info": "옥수수의 풍미를 담은 묵직한 바스크 치즈 케이크에 고소한 옥수수 크림을 가득 올린 홈메이드 스타일의 치즈 케이크",
      "image": ""
    },
    {
      "no": 6,
      "name": "떠먹는샤인머스캣우유생크림",
      "price": "6,700원",
      "info": "누구나 호불호 없이 즐길 수 있는 대중적인 고단백 저지방 우유를 활용한 우유 베이스에 샤인머스캣을 가득 올린 가볍고 산뜻한 Summer Dessert",
      "image": ""
    },
    {
      "no": 7,
      "name": "딸기초콜릿링딩동",
      "price": "6,500원",
      "info": "미국식 홈메이드 레시피인 'Ding Dong Cake'를 TWOSOME만의 스타일로 재해석, 초콜릿 가나슈로 도톰하게 코팅한 초콜릿 러버들을 위한 케이크",
      "image": ""
    },
    {
      "no": 8,
      "name": "블랙포레스트",
      "price": "6,800원",
      "info": "풍성한 생크림과 촉촉한 초콜릿 시트 사이사이에 향긋한 체리가 더해져 풍부한 맛을 살린 블랙 포레스트 조각케이크",
      "image": ""
    },
    {
      "no": 9,
      "name": "떠먹는샤인머스캣초콜릿생크림",
      "price": "6,700원",
      "info": "한가득 올린 달콤상큼한 샤인머스캣, 크런치 초코볼이 알알이 씹히는 진한 초콜릿 생크림 시트가 조화를 이루는 디저트",
      "image": ""
    },
    {
      "no": 10,
      "name": "그릭요거트딸기생크림",
      "price": "6,200원",
      "info": "딸기, 블루베리와 상큼한 베리 쥬레가 샌드되어 베리와 요거 생크림의 맛을 조화롭게 느낄 수 있는 생크림 케이크",
      "image": ""
    },
    {
      "no": 11,
      "name": "떠먹는 바닐라 슈크림",
      "price": "6,500원",
      "info": "달콤한 슈크림과 바닐라 무스, 폭신한 케이크 시트를 레이어하고 부드러운 생크림을 올려, 고소하고 바삭한 쿠키와 함께 즐기는 풍성한 구성의 떠먹는 케이크",
      "image": ""
    },
    {
      "no": 12,
      "name": "떠먹는티라미수",
      "price": "6,500원",
      "info": "마스카포네 치즈와 진한 에스프레소 시럽으로 샌드된 촉촉한 시트 위에 순도 높은 발로나 파우더를 올린 이탈리아 대표 무스 케이크 티라미수",
      "image": ""
    },
    {
      "no": 13,
      "name": "떠먹는아이스박스",
      "price": "6,500원",
      "info": "블랙쿠키 층에 마스카포네 크림의 수분이 전이되어 촉촉하고 부드럽게 즐기는 아이스박스",
      "image": ""
    },
    {
      "no": 14,
      "name": "뉴욕치즈",
      "price": "5,900원",
      "info": "부드럽고 촉촉한 식감과 진한 치즈의 향이 물씬 나는 정통 뉴욕 스타일의 구움치즈 케이크",
      "image": ""
    },
    {
      "no": 15,
      "name": "클래식가토쇼콜라",
      "price": "6,500원",
      "info": "부드러운 초코 시트에 벨기에산 다크&밀크 초콜릿 가나슈를 샌드하여 달콤하고 진하게 즐기는 초콜릿 케이크",
      "image": ""
    },
    {
      "no": 16,
      "name": "떠먹는딸기레어치즈",
      "price": "6,500원",
      "info": "상큼한 딸기퓨레와 부드러운 크림치즈, 고소한 크럼블, 라즈베리가 함께 어울려 봄을 닮은 맛의 떠먹는 케이크",
      "image": ""
    },
    {
      "no": 17,
      "name": "레드벨벳",
      "price": "6,500원",
      "info": "붉은 컬러 시트에 고소한 버터 크림치즈를 풍부하게 올려 볼륨감이 돋보이는 투썸 대표 구움 케이크",
      "image": ""
    },
    {
      "no": 18,
      "name": "퀸즈캐롯",
      "price": "6,500원",
      "info": "담백한 당근과 상큼한 오렌지 필로 식감을 살린 촉촉한 캐롯 시트와 묵직한 크림치즈를 풍성하게 레이어한 영국식 티 케이크",
      "image": ""
    },
    {
      "no": 19,
      "name": "딸기생크림",
      "price": "5,900원",
      "info": "담백한 생크림과 부드러운 시트, 딸기를 풍성하게 올린 생크림 케이크",
      "image": ""
    }
  ],
  "food": [
    {
      "no": 1,
      "name": "슈톨렌 바통 휘낭시에",
      "price": "2,700원",
      "info": "깊은 버터 풍미와 건과일, 견과류가 어우러진 긴 바통 타입으로 먹기 간편한 슈톨렌 맛 휘낭시에",
      "image": ""
    },
    {
      "no": 2,
      "name": "헤이즐넛 바통 휘낭시에",
      "price": "2,700원",
      "info": "깊은 버터 풍미와 고소한 헤이즐넛이 어우러진 긴 바통 타입으로 먹기 간편한 휘낭시에",
      "image": ""
    },
    {
      "no": 3,
      "name": "초콜릿 바통 휘낭시에",
      "price": "2,700원",
      "info": "깊은 버터 풍미와 달콤한 초콜릿이 어우러진 긴 바통 타입으로 먹기 간편한 휘낭시에",
      "image": ""
    },
    {
      "no": 4,
      "name": "그릴드베지치즈파니니",
      "price": "7,300원",
      "info": "허브 치아바타에 치폴레의 알싸함을 더한 파프리카, 쥬키니, 그린빈이 담긴 치즈 파니니",
      "image": ""
    },
    {
      "no": 5,
      "name": "트러플머쉬룸오믈렛파니니",
      "price": "7,300원",
      "info": "오트밀 깜빠뉴에 블랙트러플향을 더한 세가지 버섯과 오믈렛을 담은 담백한 파니니",
      "image": ""
    },
    {
      "no": 6,
      "name": "베리머치 듀나",
      "price": "2,800원",
      "info": "참치,옥수수,양파,샐러리를 믹스 해 풍성하게채운 브리오슈번",
      "image": ""
    },
    {
      "no": 7,
      "name": "베리머치에그",
      "price": "2,800원",
      "info": "촉촉한 에그 샐러드를 풍성하게 채운 브리오슈 번",
      "image": ""
    },
    {
      "no": 8,
      "name": "베리머치감자",
      "price": "2,800원",
      "info": "포슬포슬한 감자 샐러드를 풍성하게 채운 브리오슈 번",
      "image": ""
    },
    {
      "no": 9,
      "name": "베이컨체다베이글",
      "price": "5,500원",
      "info": "베이컨과 치즈의 풍미를 듬뿍 느낄 수 있는 뉴욕식 핫 베이글",
      "image": ""
    },
    {
      "no": 10,
      "name": "윌넛초코칩쿠키",
      "price": "3,000원",
      "info": "밀크, 다크초콜릿, 호두분태 토핑의 두툼한 점보 쿠키",
      "image": ""
    },
    {
      "no": 11,
      "name": "무화과스콘",
      "price": "3,800원",
      "info": "톡톡 씹히는 무화과가 달콤한 스콘",
      "image": ""
    },
    {
      "no": 12,
      "name": "바베큐치킨파니니",
      "price": "6,900원",
      "info": "바베큐 소스를 곁들인 치킨을 넣은 바베큐치킨파니니",
      "image": ""
    },
    {
      "no": 13,
      "name": "멕시칸파니니",
      "price": "6,900원",
      "info": "데리야끼 치킨, 볶은 파프리카, 후레쉬 모짜렐라 치즈를 넣은 멕시칸파니니",
      "image": ""
    },
    {
      "no": 14,
      "name": "페스토햄치즈파니니",
      "price": "6,900원",
      "info": "올리브 치아바타에 바질 페스토, 닭가슴살 햄, 후레쉬 모짜렐라 치즈, 토마토를 곁들인 따뜻한 샌드위치",
      "image": ""
    },
    {
      "no": 15,
      "name": "스크램볼에그샌드위치",
      "price": "5,500원",
      "info": "부드러운 우유식빵에 스크램블 에그와 베이컨, 치즈가 어우러진 샌드위치",
      "image": ""
    },
    {
      "no": 16,
      "name": "크로크무슈",
      "price": "4,800원",
      "info": "두툼한 식빵에 쫄깃한 햄과 뮌스터 치즈를 넣은 담백하고 든든한 샌드위치",
      "image": ""
    },
    {
      "no": 17,
      "name": "생미쉘시트러스마들렌",
      "price": "2,500원",
      "info": "상큼한 오렌지, 만다린필로 향긋하고 부드러운 마들렌",
      "image": ""
    },
    {
      "no": 18,
      "name": "플레인베이글(with크림치즈)",
      "price": "3,800원",
      "info": "고소한 곡물향을 느낄 수 있는 사워도우 베이글",
      "image": ""
    }
  ],
  "macaron": [
    {
      "no": 1,
      "name": "황치즈마카롱",
      "price": "2,400원",
      "info": "달콤한 크림치즈와 짭짤한 체다치즈의 풍미가 가득한 단짠단짠한 매력의 마카롱",
      "image": ""
    },
    {
      "no": 2,
      "name": "청포도요거트마카롱",
      "price": "2,400원",
      "info": "청포도잼을 더한 요거트 크림을 샌딩하여 더욱 상큼하고 청량한 풍미를 즐길 수 있는 마카롱",
      "image": ""
    },
    {
      "no": 3,
      "name": "커스터드바닐라다쿠아즈에뻬",
      "price": "3,000원",
      "info": "폭신폭신한 비스퀴 사이에 달콤한 풍미의 크리미한 바닐라 크림이 더해져 입 안 가득 풍부한 맛과 향이 느껴지는 다쿠아즈",
      "image": ""
    },
    {
      "no": 4,
      "name": "다크초콜릿다쿠아즈에뻬",
      "price": "3,000원",
      "info": "폭신폭신한 비스퀴 사이에 다크 초콜릿의 달콤 쌉싸름함과 생크림의 부드러움이 균형을 이루는 진하고 묵직한 필링으로 완성한 다쿠아즈",
      "image": ""
    },
    {
      "no": 5,
      "name": "그린티가나슈다쿠아즈에뻬",
      "price": "3,000원",
      "info": "폭신폭신한 비스퀴 사이에 진한 풍미의 국내산 녹차 크림과 달콤한 화이트 초콜릿 그린티 가나슈 필링이 어우러진 다쿠아즈",
      "image": ""
    },
    {
      "no": 6,
      "name": "다쿠아즈에뻬세트(3개입)",
      "price": "10,500원",
      "info": "폭신폭신한 비스퀴 사이에 입안 가득 퍼지는 달콤하고 진한 풍미의 필링이 어우러진 다쿠아즈를 한 번에 맛 볼 수 있는 세트 제품",
      "image": ""
    },
    {
      "no": 7,
      "name": "다쿠아즈에뻬세트(6개입)",
      "price": "20,000원",
      "info": "폭신폭신한 비스퀴 사이에 입안 가득 퍼지는 달콤하고 진한 풍미의 필링이 어우러진 다쿠아즈를 한 번에 맛 볼 수 있는 세트 제품",
      "image": ""
    },
    {
      "no": 8,
      "name": "산딸기마카롱",
      "price": "2,400원",
      "info": "품질좋은 산딸기 퓨레를 사용하여 진짜 산딸기를 먹는 듯한 새콤달콤함을 느낄 수 있는 마카롱",
      "image": ""
    },
    {
      "no": 9,
      "name": "블루베리마카롱",
      "price": "2,400원",
      "info": "화이트가나슈와 블루베리 원물이 조화롭게 어우러지는 마카롱",
      "image": ""
    },
    {
      "no": 10,
      "name": "벨지안초콜릿마카롱",
      "price": "2,400원",
      "info": "프리미엄 초콜릿을 사용하여 깊고 진한 카카오의 풍미가 느껴지는 마카롱",
      "image": ""
    },
    {
      "no": 11,
      "name": "마다가스카르바닐라마카롱",
      "price": "2,400원",
      "info": "마다가스카르 바닐라빈이 듬뿍 들어간 가나슈가 특징인 달콤한 마카롱",
      "image": ""
    },
    {
      "no": 12,
      "name": "투썸마카롱세트(12개입)",
      "price": "30,000원",
      "info": "다양하고 생생한 컬러, 풍부한 크림의 촉촉한 부드로움, 입안 가득 퍼지는 달콤한 마카롱을 한번에 맛볼수있는 세트제품",
      "image": ""
    }
  ],
  "cookieAndsnack": [
    {
      "no": 1,
      "name": "마카다미아 오너먼트 초콜릿",
      "price": "5,700원",
      "info": "풍성한 통 마카다미아에 초콜릿으로 달콤함을 더한 오너먼트형 스몰 기프트 초콜릿",
      "image": ""
    },
    {
      "no": 2,
      "name": "스노우볼 오너먼트 쿠키",
      "price": "5,700원",
      "info": "고소한 아몬드 가루에 슈가 파우더로 달콤함을 더한 오너먼트형 스몰 기프트 쿠키",
      "image": ""
    },
    {
      "no": 3,
      "name": "촉촉한 우리 찐밤",
      "price": "3,200원",
      "info": "100% 국내산 알밤을 껴서 만든 포슬포슬하고 달큰한 건강간식",
      "image": ""
    },
    {
      "no": 4,
      "name": "우리쌀튀일",
      "price": "5,800원",
      "info": "정성스럽게 볶은 우리 현미와 백미로 바삭하고 고소한 튀일",
      "image": ""
    },
    {
      "no": 5,
      "name": "아몬드코코넛튀일",
      "price": "5,800원",
      "info": "아몬드 튀일에 코코넛 칩 토핑을 더해 바삭하고 고소하게 즐기는 쿠키",
      "image": ""
    },
    {
      "no": 6,
      "name": "골든치즈사블레",
      "price": "5,800원",
      "info": "에담치즈를 넣은 쿠키에 파마산 치즈를 토핑해 짭짤하고 부드러운 사블레 쿠키",
      "image": ""
    },
    {
      "no": 7,
      "name": "바통쇼콜라",
      "price": "5,800원",
      "info": "진한 코코아의 맛이 콕콕 박힌 아몬드 칩과 함께 느껴지는 스틱형태의 초콜릿 쿠키",
      "image": ""
    },
    {
      "no": 8,
      "name": "그릭요거트그래놀라바",
      "price": "1,800원",
      "info": "6가지 곡물과 산뜻한 그릭요거트 맛이 어우러진 그래놀라 바",
      "image": ""
    },
    {
      "no": 9,
      "name": "너츠앤푸르츠",
      "price": "2,800원",
      "info": "고소한 피칸, 캐슈넛, 아몬드와 달콤한 홀 크랜베리, 애플 큐브로 구성된 든든한 견과 믹스",
      "image": ""
    },
    {
      "no": 10,
      "name": "고구마바",
      "price": "1,400원",
      "info": "국내산 고구마를 껍질째 쪄서 더욱 촉촉하고 달콤한 건강 간식",
      "image": ""
    }
  ],
  "goods": [
    {
      "no": 1,
      "name": "투썸에이리스트 핸드드립커피 그리너리블렌드",
      "price": "6,900원",
      "info": "산뜻한 청사과의 향이 은은하며, 고소한 견과류의 풍미와 브라운 슈가의 단맛으로 뛰어난 균형을 이루는 블렌딩커피",
      "image": ""
    },
    {
      "no": 2,
      "name": "투썸원두_파푸아뉴기니올리아",
      "price": "17,000원",
      "info": "잘 익은 핵과를 한 입 베어 문 듯, 달콤하고 화사한 플레이버의 원두 [Tasting Note : Stone fruit, Mangosteen, Syrupy]",
      "image": ""
    },
    {
      "no": 3,
      "name": "투썸원두_괴테말라안티구아",
      "price": "17,000원",
      "info": "짙은 와이니함과 고소한 견과류의 풍미가 매력적인 원두 [Tasting Note : Rasin, Winy, Cashew nut]",
      "image": ""
    },
    {
      "no": 4,
      "name": "콜드브루 디카페인원액",
      "price": "14,900원",
      "info": "가정에서 즐기는 깊고 진한 투썸 에이리스트 디카페인 콜드브루 커피원액500ml [Tasting Note , Well/Balanced, Sweet, Rich]",
      "image": ""
    },
    {
      "no": 5,
      "name": "투썸원두_블랙그라운드",
      "price": "15,000원",
      "info": "깊고 진한 블랙 그라운드 [Tasting Note: Full/body, Nutty, Dark Chocolaty]",
      "image": ""
    },
    {
      "no": 6,
      "name": "투썸원두_아로마노트",
      "price": "16,000원",
      "info": "산뜻한 풍미의 개성있는 아로마노트 [Tasting Note: Berry/like, Juicy, Floral]",
      "image": ""
    },
    {
      "no": 7,
      "name": "투썸원두_디카페인",
      "price": "17,000원",
      "info": "견과류의 고소함과 은은한 단맛이 조화로운 디카페인 원두 [Tasting Note : Rich, Sweet, Well Balanced]",
      "image": ""
    },
    {
      "no": 8,
      "name": "투썸에이리스트_스틱커피",
      "price": "4,800원",
      "info": "풍부한 바디감과 은은한 단맛이 균형감을 이루는 커피",
      "image": ""
    },
    {
      "no": 9,
      "name": "투썸에이리스트_스틱커피(디카페인)",
      "price": "5,300원",
      "info": "간편한 스틱형 커피로 견과류의 고소함과 은은한 단맛이 조화를이루는 커피",
      "image": ""
    },
    {
      "no": 10,
      "name": "투썸에이리스트_바닐라라떼",
      "price": "6,500원",
      "info": "진한 커피의 향과 리치한 바닐라의 달콤한 풍미가 조화롭게 어울리는 라떼스틱",
      "image": ""
    },
    {
      "no": 11,
      "name": "투썸에이리스트_초콜렛라떼",
      "price": "7,000원",
      "info": "깊고 진한 초콜릿을 부드러운 우유와 함께 즐길 수 있는 달콤한 라떼스틱",
      "image": ""
    },
    {
      "no": 12,
      "name": "콜드브루원액",
      "price": "14,000원",
      "info": "가정에서 즐기는 깊고 진한 투썸 에이리스트 콜드브루 커피원액500ml [Tasting Note, Full/body, Nutty, Rich]",
      "image": ""
    },
    {
      "no": 13,
      "name": "투썸에이리스트_핸드드립커피(블랙그라운드)",
      "price": "6,500원",
      "info": "가정에서 즐기는 투썸 핸드드립커피",
      "image": ""
    },
    {
      "no": 14,
      "name": "투썸에이리스트_핸드드립커피(아로마노트)",
      "price": "6,500원",
      "info": "가정에서 즐기는 투썸 핸드드립커피",
      "image": ""
    },
    {
      "no": 15,
      "name": "투썸에이리스트_핸드드립커피(디카페인)",
      "price": "7,000원",
      "info": "가정에서 즐기는 투썸 핸드드립커피",
      "image": ""
    },
    {
      "no": 16,
      "name": "투썸에이리스트_캡슐커피(바닐라향브리즈)",
      "price": "7,600원",
      "info": "파푸아뉴기니와 브라질의 원두를 블렌딩하여 균형있는 커피의 풍미를 구현하고 바닐라 플레이버로 향의 조화를 극대화한 캡슐커피",
      "image": ""
    },
    {
      "no": 17,
      "name": "투썸에이리스트_캡슐커피(블랙그라운드)",
      "price": "7,600원",
      "info": "가정에서 즐기는 투썸 캡슐커피, 중남미 산지 원두를 블렌딩하여 다크초콜릿과 입안가득 꽉 찬 바디감이 느껴지는 블랙그라운드 [네스프레소 커피머신 호환 가능]",
      "image": ""
    },
    {
      "no": 18,
      "name": "투썸에이리스트_캡슐커피(아로마노트)",
      "price": "7,800원",
      "info": "가정에서 즐기는 투썸 캡슐커피, 에티오피아 산지의 원두를 블렌딩하여 싱그러운 과일과 플로럴한 아로마가 느껴지는 아로마노트 [네스프레소 커피머신 호환 가능]",
      "image": ""
    },
    {
      "no": 19,
      "name": "투썸에이리스트_캡슐커피(디카페인)",
      "price": "8,100원",
      "info": "친환경 방식으로 카페인을 제거한 견과류의 고소함이 느꺄지는 원두로 은은한 단맛이 균형을 이루는 커피 / 네스프레소 캡슐머신 호환",
      "image": ""
    }
  ]
}
